<?xml version="1.0" encoding="UTF-8"?>
<!DOCTYPE suite SYSTEM "https://testng.org/testng-1.0.dtd">
<suite name="Suite">
<listeners>
<listener class-name="com.neo360.listners.ResultListener"></listener>
</listeners>
  <test thread-count="5" name="Test">
    <classes>
      <class name="com.neo360.test.website.CCNsight.CCNsightWithInCircleOnDailyWeeklyAndMonthlyBasisTest"/>
      <class name="com.neo360.test.website.CCNsight.CCNsightAcrossCircleWithIndividualCircleOnDailyWeeklyAndMonthlyBasisTest"/>
      <class name="com.neo360.test.website.CCNsight.CCNsightAcrossCircleWithMultipleCircleOnDailyWeeklyAndMonthlyBasisTest"/>
        <class name="com.neo360.test.website.CCNsight.CCNsightIndividualSubScriberCircleSelectionTest"/>
    </classes>
  </test> <!-- Test -->
</suite> <!-- Suite -->
